dynawrap/__init__.py
dynawrap/_version.py
dynawrap/dbitem.py
dynawrap/dynamodb.py
dynawrap/model_registry.py
dynawrap-0.3.8.dist-info/METADATA
dynawrap-0.3.8.dist-info/WHEEL
dynawrap-0.3.8.dist-info/top_level.txt
dynawrap-0.3.8.dist-info/RECORD
