Metadata-Version: 2.4
Name: dynawrap
Version: 0.3.8
Summary: Lightweight wrapper to handle access pattern management to AWS DynamoDB tables
Home-page: https://github.com/bayinfosys/aws-dynamodb-wrapper
Author: Ed Grundy
Author-email: ed@bayis.co.uk
Classifier: Programming Language :: Python :: 3
Classifier: License :: OSI Approved :: MIT License
Classifier: Operating System :: OS Independent
Requires-Python: >=3.7
Requires-Dist: parse
Provides-Extra: dev
Requires-Dist: pytest; extra == "dev"
Requires-Dist: black; extra == "dev"
Requires-Dist: flake8; extra == "dev"
Provides-Extra: local
Requires-Dist: boto3; extra == "local"
Dynamic: author
Dynamic: author-email
Dynamic: classifier
Dynamic: description
Dynamic: description-content-type
Dynamic: home-page
Dynamic: provides-extra
Dynamic: requires-dist
Dynamic: requires-python
Dynamic: summary
